HAI_Bot/ChatBot.py
HAI_Bot/ChatBot.pyi
HAI_Bot/__init__.py
HAI_Bot-0.4.dist-info/LICENSE
HAI_Bot-0.4.dist-info/METADATA
HAI_Bot-0.4.dist-info/WHEEL
HAI_Bot-0.4.dist-info/top_level.txt
HAI_Bot-0.4.dist-info/RECORD
