Metadata-Version: 2.1
Name: HAI_Bot
Version: 0.4
Summary: A Python package for creating ChatBot with your own data
Home-page: https://github.com/HDAI654/HAI_Bot
Author: Hamed Amiri
Author-email: your.email@example.com
License: MIT
Classifier: Programming Language :: Python :: 3
Classifier: Operating System :: OS Independent
Classifier: License :: OSI Approved :: MIT License
Requires-Python: >=3.6
License-File: LICENSE
Requires-Dist: keras
Requires-Dist: numpy
